sizemeup/__init__.py
sizemeup/atb.py
sizemeup/cli/__init__.py
sizemeup/cli/build.py
sizemeup/cli/sizemeup.py
sizemeup/ncbi.py
sizemeup/utils.py
sizemeup-1.3.0.dist-info/LICENSE
sizemeup-1.3.0.dist-info/METADATA
sizemeup-1.3.0.dist-info/WHEEL
sizemeup-1.3.0.dist-info/entry_points.txt
sizemeup-1.3.0.dist-info/RECORD
