Metadata-Version: 2.1
Name: sizemeup
Version: 1.3.0
Summary: A simple tool to determine the genome size of an organism
Home-page: https://github.com/rpetit3/sizemeup
License: MIT
Keywords: bioinformatics,genome size
Author: Robert A. Petit III
Author-email: robbie.petit@gmail.com
Requires-Python: >=3.8.1,<4.0.0
Classifier: License :: OSI Approved :: MIT License
Classifier: Programming Language :: Python :: 3
Classifier: Programming Language :: Python :: 3.9
Classifier: Programming Language :: Python :: 3.10
Classifier: Programming Language :: Python :: 3.11
Classifier: Programming Language :: Python :: 3.12
Requires-Dist: requests (>=2.32.3,<3.0.0)
Requires-Dist: rich (>=13.7.1,<14.0.0)
Requires-Dist: rich-click (>=1.7.4,<2.0.0)
Project-URL: Repository, https://github.com/rpetit3/sizemeup
